formelsammlung/__init__.py
formelsammlung/env_exe_runner.py
formelsammlung/envvar.py
formelsammlung/flask_sphinx_docs.py
formelsammlung/nox_session.py
formelsammlung/py.typed
formelsammlung/strcalc.py
formelsammlung/venv_utils.py
formelsammlung-5.0.0.dist-info/entry_points.txt
formelsammlung-5.0.0.dist-info/LICENSE
formelsammlung-5.0.0.dist-info/WHEEL
formelsammlung-5.0.0.dist-info/METADATA
formelsammlung-5.0.0.dist-info/RECORD
