Metadata-Version: 2.1
Name: formelsammlung
Version: 5.0.0
Summary: Collection of different functions
License: GPL-3.0-or-later
Author: Christian Riedel
Author-email: cielquan@protonmail.com
Requires-Python: >=3.6.2,<4.0.0
Classifier: Development Status :: 5 - Production/Stable
Classifier: Intended Audience :: Developers
Classifier: License :: OSI Approved :: GNU General Public License v3 or later (GPLv3+)
Classifier: Natural Language :: English
Classifier: Operating System :: MacOS
Classifier: Operating System :: Microsoft :: Windows :: Windows 10
Classifier: Operating System :: POSIX :: Linux
Classifier: Programming Language :: Python :: 3
Classifier: Programming Language :: Python :: 3.10
Classifier: Programming Language :: Python :: 3.6
Classifier: Programming Language :: Python :: 3.7
Classifier: Programming Language :: Python :: 3.8
Classifier: Programming Language :: Python :: 3.9
Classifier: Programming Language :: Python :: Implementation :: CPython
Classifier: Programming Language :: Python :: Implementation :: PyPy
Classifier: Topic :: Software Development
Classifier: Topic :: Utilities
Provides-Extra: coverage
Provides-Extra: dev_nox
Provides-Extra: diff-cover
Provides-Extra: docs
Provides-Extra: flask
Provides-Extra: nox
Provides-Extra: poetry
Provides-Extra: pre-commit
Provides-Extra: safety
Provides-Extra: sphinx-autobuild
Provides-Extra: testing
Provides-Extra: tomlkit
Provides-Extra: tox
Provides-Extra: twine
Requires-Dist: bandit (>=1.7,<2.0); extra == "pre-commit"
Requires-Dist: coverage-conditional-plugin (>=0.3.1,<0.4.0); extra == "testing" or extra == "coverage"
Requires-Dist: coverage[toml] (>=5.3.1,<6.0.0); extra == "testing" or extra == "coverage"
Requires-Dist: diff-cover (>=4,<5); extra == "diff-cover"
Requires-Dist: flake8 (>=3.8,<4.0); extra == "pre-commit"
Requires-Dist: flake8-2020 (>=1.6,<2.0); extra == "pre-commit"
Requires-Dist: flake8-aaa (>=0.11,<0.12); extra == "pre-commit"
Requires-Dist: flake8-annotations (>=2.4,<3.0); extra == "pre-commit"
Requires-Dist: flake8-bandit (>=2.1.2,<3.0.0); extra == "pre-commit"
Requires-Dist: flake8-broken-line (>=0.3,<0.4); extra == "pre-commit"
Requires-Dist: flake8-bugbear (>=20.11,<21.0); extra == "pre-commit"
Requires-Dist: flake8-cognitive-complexity (>=0.1,<0.2); extra == "pre-commit"
Requires-Dist: flake8-comprehensions (>=3.3,<4.0); extra == "pre-commit"
Requires-Dist: flake8-docstrings (>=1.5,<2.0); extra == "pre-commit"
Requires-Dist: flake8-eradicate (>=1,<2); extra == "pre-commit"
Requires-Dist: flake8-logging-format (>=0.6,<0.7); extra == "pre-commit"
Requires-Dist: flake8-mutable (>=1.2,<2.0); extra == "pre-commit"
Requires-Dist: flake8-no-u-prefixed-strings (>=0.2,<0.3); extra == "pre-commit"
Requires-Dist: flake8-pytest-style (>=1.3,<2.0); extra == "pre-commit"
Requires-Dist: flake8-rst-docstrings (>=0.0.14,<0.0.15); extra == "pre-commit"
Requires-Dist: flake8-simplify (>=0.12,<0.13); extra == "pre-commit"
Requires-Dist: flake8-sql (>=0.4.1,<0.5.0); extra == "pre-commit"
Requires-Dist: flake8-string-format (>=0.3,<0.4); extra == "pre-commit"
Requires-Dist: flake8-typing-imports (>=1.10.1,<2.0.0); extra == "pre-commit"
Requires-Dist: flake8-use-fstring (>=1.1,<2.0); extra == "pre-commit"
Requires-Dist: flake8-variables-names (>=0.0.3,<0.0.4); extra == "pre-commit"
Requires-Dist: flake8-walrus (>=1.1,<2.0); (python_version >= "3.8") and (extra == "pre-commit")
Requires-Dist: flakehell (==0.8.0); extra == "pre-commit"
Requires-Dist: flask (>=1.1.2,<2.0.0); extra == "flask" or extra == "testing" or extra == "docs"
Requires-Dist: importlib-metadata (>=1.6,<4.0); python_version < "3.8"
Requires-Dist: m2r2 (>=0.2.7,<0.3.0); extra == "docs"
Requires-Dist: mock (>=4.0.3,<5.0.0); extra == "testing"
Requires-Dist: mypy (==0.790); extra == "pre-commit"
Requires-Dist: nox (>=2020.12.31,<2021.0.0); extra == "nox" or extra == "testing" or extra == "docs" or extra == "dev_nox"
Requires-Dist: pep8-naming (>=0.11,<0.12); extra == "pre-commit"
Requires-Dist: poetry (>=1.1.4,<2.0.0); extra == "poetry"
Requires-Dist: pre-commit (>=2.9,<3.0); extra == "pre-commit"
Requires-Dist: psutil (>=5.8.0,<6.0.0); extra == "testing"
Requires-Dist: pydocstyle (>=5.1,<6.0)
Requires-Dist: pyenchant (>=3.2,<4.0); extra == "pre-commit"
Requires-Dist: pylint (>=2.6,<3.0); extra == "pre-commit"
Requires-Dist: pytest (>=6,<7); extra == "testing"
Requires-Dist: pytest-cov (>=2.10.1,<3.0.0); extra == "testing"
Requires-Dist: pytest-flask (>=1.0,<2.0); extra == "testing"
Requires-Dist: pytest-mock (>=3.5.1,<4.0.0); extra == "testing"
Requires-Dist: pytest-randomly (>=3.5,<4.0); extra == "testing"
Requires-Dist: pytest-sugar (>=0.9.4,<0.10.0); extra == "testing"
Requires-Dist: pytest-xdist (>=2.2,<3.0); extra == "testing"
Requires-Dist: python-dotenv (>=0.15,<0.16)
Requires-Dist: safety (>=1.9,<2.0); extra == "safety"
Requires-Dist: sphinx (>=3.1,<4.0); extra == "docs" or extra == "pre-commit"
Requires-Dist: sphinx-autobuild (==2020.9.1); extra == "sphinx-autobuild"
Requires-Dist: sphinx-autodoc-typehints (>=1.11,<2.0); extra == "docs"
Requires-Dist: sphinx-rtd-theme (>=0.5.1,<0.6.0); extra == "docs"
Requires-Dist: sphinxcontrib-apidoc (>=0.3,<0.4); extra == "docs"
Requires-Dist: sphinxcontrib-spelling (>=7.1,<8.0); extra == "docs"
Requires-Dist: tomlkit (>=0.7.0,<1.0.0); extra == "dev_nox" or extra == "tomlkit"
Requires-Dist: tox (>=3.21,<4.0); extra == "tox"
Requires-Dist: twine (>=3.3,<4.0); extra == "twine"
Project-URL: Changelog, https://formelsammlung.readthedocs.io/en/latest/changelog
Project-URL: Documentation, https://formelsammlung.readthedocs.io
Project-URL: Issue Tracker, https://github.com/Cielquan/formelsammlung/issues
Project-URL: Source, https://github.com/Cielquan/formelsammlung
